{
  "width": 11.9,
  "height": 6.5,
  "area": 38.675000000000004,
  "moduleWidth": 1.134,
  "moduleHeight": 1.722,
  "rotation": 0,
  "power": 430,
  "voc": 38.4,
  "current": 13,
  "mittelstegweite": 0.03,
  "verbotszone": 0.3,
  "modules": [
    {
      "id": 1767295151648,
      "left": 6.2536249999999995,
      "width": 1.134,
      "top": 0.08,
      "rotation": 90
    },
    {
      "id": 1767295341556,
      "left": 8.012199999999998,
      "width": 1.134,
      "top": 0.07999999999999947,
      "rotation": 90
    },
    {
      "id": 1767295352536,
      "left": 4.497325000000002,
      "width": 1.134,
      "top": 0.08,
      "rotation": 90
    },
    {
      "id": 1767295358587,
      "left": 2.743125,
      "width": 1.134,
      "top": 0.07999999999999947,
      "rotation": 90
    },
    {
      "id": 1767295378184,
      "left": 5.383,
      "width": 1.134,
      "top": 1.2500491790771477,
      "rotation": 90
    },
    {
      "id": 1767295382930,
      "left": 7.157500000000001,
      "width": 1.134,
      "top": 1.2500491790771477,
      "rotation": 90
    },
    {
      "id": 1767295389480,
      "left": 3.618125,
      "width": 1.134,
      "top": 1.2500491790771477,
      "rotation": 90
    },
    {
      "id": 1767295404954,
      "left": 6.286875,
      "width": 1.134,
      "top": 2.418754699707031,
      "rotation": 90
    },
    {
      "id": 1767295410660,
      "left": 4.497325000000002,
      "width": 1.134,
      "top": 2.418754699707031,
      "rotation": 90
    },
    {
      "id": 1767295415517,
      "left": 5.383,
      "width": 1.134,
      "top": 3.587460754394531,
      "rotation": 90
    }
  ],
  "updatedAt": "2026-01-01T21:53:17.366Z"
}